LICENSE
MANIFEST.in
README.md
setup.cfg
setup.py
indicator/__init__.py
indicator/base.py
indicator/expert.py
indicator/tlb.py
indicator.egg-info/PKG-INFO
indicator.egg-info/SOURCES.txt
indicator.egg-info/dependency_links.txt
indicator.egg-info/requires.txt
indicator.egg-info/top_level.txt
indicator/technology/__init__.py
indicator/technology/average.py
indicator/technology/chat.py
indicator/technology/countertrend.py
indicator/technology/dragon.py
indicator/technology/energy.py
indicator/technology/generaltrend.py
indicator/technology/ghost.py
indicator/technology/god.py
indicator/technology/pressure.py
indicator/technology/quantity.py
indicator/technology/route.py
indicator/technology/transactional.py
indicator/technology/trend.py