Metadata-Version: 2.1
Name: indicator
Version: 1.0.6
Summary: Solving Quantitative Indicators of Funds, Stocks and Foreign Exchange Tool
Home-page: https://github.com/haibeicode/indicator
Author: Tab
Author-email: ns_v@sina.com
License: Apache 2.0
Keywords: Financial Indicator Tool
Platform: UNKNOWN
License-File: LICENSE
